RancherShizhanHongbaoshu/README.md
RancherShizhanHongbaoshu/__init__.py
RancherShizhanHongbaoshu/__main__.py
RancherShizhanHongbaoshu/file.epub
RancherShizhanHongbaoshu/index.html
RancherShizhanHongbaoshu/css/__init__.py
RancherShizhanHongbaoshu/css/annotations.css
RancherShizhanHongbaoshu/css/main.css
RancherShizhanHongbaoshu/css/normalize.css
RancherShizhanHongbaoshu/css/popup.css
RancherShizhanHongbaoshu/font/__init__.py
RancherShizhanHongbaoshu/font/fontello.eot
RancherShizhanHongbaoshu/font/fontello.svg
RancherShizhanHongbaoshu/font/fontello.ttf
RancherShizhanHongbaoshu/font/fontello.woff
RancherShizhanHongbaoshu/img/__init__.py
RancherShizhanHongbaoshu/img/annotator-glyph-sprite.png
RancherShizhanHongbaoshu/img/annotator-icon-sprite.png
RancherShizhanHongbaoshu/img/apple-touch-icon.png
RancherShizhanHongbaoshu/img/cancelfullscreen.png
RancherShizhanHongbaoshu/img/close.png
RancherShizhanHongbaoshu/img/fullscreen.png
RancherShizhanHongbaoshu/img/loader.gif
RancherShizhanHongbaoshu/img/menu-icon.png
RancherShizhanHongbaoshu/img/save.png
RancherShizhanHongbaoshu/img/saved.png
RancherShizhanHongbaoshu/img/settings-s.png
RancherShizhanHongbaoshu/img/settings.png
RancherShizhanHongbaoshu/img/star.png
RancherShizhanHongbaoshu/js/__init__.py
RancherShizhanHongbaoshu/js/epub.js
RancherShizhanHongbaoshu/js/epub.min.js
RancherShizhanHongbaoshu/js/epub.min.map
RancherShizhanHongbaoshu/js/hooks.min.js
RancherShizhanHongbaoshu/js/hooks.min.map
RancherShizhanHongbaoshu/js/reader.js
RancherShizhanHongbaoshu/js/reader.js.map
RancherShizhanHongbaoshu/js/reader.min.js
RancherShizhanHongbaoshu/js/reader.min.map
RancherShizhanHongbaoshu/js/hooks/__init__.py
RancherShizhanHongbaoshu/js/hooks/extensions/__init__.py
RancherShizhanHongbaoshu/js/hooks/extensions/highlight.js
RancherShizhanHongbaoshu/js/libs/__init__.py
RancherShizhanHongbaoshu/js/libs/jquery.min.js
RancherShizhanHongbaoshu/js/libs/localforage.min.js
RancherShizhanHongbaoshu/js/libs/screenfull.js
rancher_shizhan_hongbaoshu-2024.3.4.0.dist-info/METADATA
rancher_shizhan_hongbaoshu-2024.3.4.0.dist-info/WHEEL
rancher_shizhan_hongbaoshu-2024.3.4.0.dist-info/entry_points.txt
rancher_shizhan_hongbaoshu-2024.3.4.0.dist-info/top_level.txt
rancher_shizhan_hongbaoshu-2024.3.4.0.dist-info/RECORD
